{"font_size":0.4,"font_color":"#FFFFFF","background_alpha":0.5,"background_color":"#9C27B0","Stroke":"none","body":[{"from":0,"to":4.3,"location":2,"content":"[MUSIC PLAYING]"},{"from":4.3,"to":10.21,"location":2,"content":" "},{"from":10.21,"to":10.71,"location":2,"content":"{}"},{"from":10.71,"to":13.41,"location":2,"content":"WILL WRIGHT: There are\ntools, or mechanisms,"},{"from":13.41,"to":16.32,"location":2,"content":"or patterns of\ninteraction that you can"},{"from":16.32,"to":18.27,"location":2,"content":"use that you have the player--"},{"from":18.27,"to":21.24,"location":2,"content":"this kind of creativity,\nthis kind of affordance,"},{"from":21.24,"to":22.17,"location":2,"content":"this kind of agency."},{"from":22.17,"to":24.38,"location":2,"content":"Underneath the hood, you\nknow, the game is actually--"},{"from":24.38,"to":25.14,"location":2,"content":"[BABY CRIES]"},{"from":25.14,"to":27.33,"location":2,"content":"--doing some causal\nconnection between when"},{"from":27.33,"to":29.85,"location":2,"content":"the player does\nthat, this happens,"},{"from":29.85,"to":30,"location":2,"content":"or here's the limitation."},{"from":30,"to":32.1,"location":2,"content":"or here's the limitation."},{"from":32.1,"to":34.98,"location":2,"content":"And it really kind of comes down\nto an affordance or an action"},{"from":34.98,"to":36.9,"location":2,"content":"that the player is\nallowed in a game"},{"from":36.9,"to":39.27,"location":2,"content":"and how the game\nresponse to that action,"},{"from":39.27,"to":42.47,"location":2,"content":"and it kind of defines\nwhat the challenge is."},{"from":42.47,"to":44.85,"location":2,"content":"If it's a locked door,\nwhat is the puzzle, or what"},{"from":44.85,"to":48.63,"location":2,"content":"are the items needed\nto unlock that door?"},{"from":48.63,"to":50.67,"location":2,"content":"If it's an exploration\nthing, what path"},{"from":50.67,"to":53.97,"location":2,"content":"do you have to take through\nthis maze to get to the exit?"},{"from":53.97,"to":55.92,"location":2,"content":"If it's a resource\nallocation thing,"},{"from":55.92,"to":58.2,"location":2,"content":"it's what are the\nbasic resources?"},{"from":58.2,"to":59.25,"location":2,"content":"How they being consumed?"},{"from":59.25,"to":60,"location":2,"content":"How are they being earned?"},{"from":60,"to":60.36,"location":2,"content":"How are they being earned?"},{"from":60.36,"to":62.78,"location":2,"content":"Each one of these is kind of\nwhat we call a game mechanic."},{"from":62.78,"to":67.2,"location":2,"content":"They're like little closed\nsystem of somehow interaction,"},{"from":67.2,"to":70.98,"location":2,"content":"balance, economy that\nyou can connect together"},{"from":70.98,"to":73.68,"location":2,"content":"to make a larger\ninteractive experience."},{"from":73.68,"to":80.92,"location":2,"content":" "},{"from":80.92,"to":83.09,"location":2,"content":"Mechanic is some kind\nof process going on"},{"from":83.09,"to":86.73,"location":2,"content":"between the player and the game\nthat you might attach metrics"},{"from":86.73,"to":87.23,"location":2,"content":"to you."},{"from":87.23,"to":90,"location":2,"content":"Might attach a leaderboard\nor scoring system to that."},{"from":90,"to":91.26,"location":2,"content":"Might attach a leaderboard\nor scoring system to that."},{"from":91.26,"to":94.43,"location":2,"content":"But once you have that,\nthat process going on,"},{"from":94.43,"to":95.99,"location":2,"content":"you can now use\nthat process either"},{"from":95.99,"to":98.63,"location":2,"content":"to moderate the\nplayer's progress."},{"from":98.63,"to":102.82,"location":2,"content":"You can use that process to,\nyou know, add difficulty."},{"from":102.82,"to":104.78,"location":2,"content":"You can use that process\nto make the world more"},{"from":104.78,"to":108.45,"location":2,"content":"interesting, more mysterious,\nmore kind of tangible."},{"from":108.45,"to":109.82,"location":2,"content":"You know, there\nare a lot of ways"},{"from":109.82,"to":111.92,"location":2,"content":"to use these kind of\nwhat I'd call, like,"},{"from":111.92,"to":115.1,"location":2,"content":"micro processes to build up\nthat larger process of here's"},{"from":115.1,"to":117.41,"location":2,"content":"what it feels like\nto be in that world."},{"from":117.41,"to":120,"location":2,"content":"In some sense, I think,\nof this as the dynamics."},{"from":120,"to":120.32,"location":2,"content":"In some sense, I think,\nof this as the dynamics."},{"from":120.32,"to":122.36,"location":2,"content":"You know, as a player's\ndoing things in the game,"},{"from":122.36,"to":124.33,"location":2,"content":"how is that game\nresponding to the player?"},{"from":124.33,"to":126.5,"location":2,"content":"You know, what is the\nconversation that the player's"},{"from":126.5,"to":129.41,"location":2,"content":"having with the game system?"},{"from":129.41,"to":134.51,"location":2,"content":"And each one of these mechanics\nis kind of one type of phrase,"},{"from":134.51,"to":136.82,"location":2,"content":"or interaction,\nor you know, word"},{"from":136.82,"to":139.58,"location":2,"content":"the player can kind of\nexpress within that system"},{"from":139.58,"to":142.43,"location":2,"content":"against the game, and the game\nwill respond in certain ways,"},{"from":142.43,"to":143.87,"location":2,"content":"and the player's\nkind of learning"},{"from":143.87,"to":146.63,"location":2,"content":"to kind of converse\nwith the game system"},{"from":146.63,"to":147.95,"location":2,"content":"through these mechanics."},{"from":147.95,"to":150,"location":2,"content":"[MUSIC PLAYING]"},{"from":150,"to":154.67,"location":2,"content":"[MUSIC PLAYING]"},{"from":154.67,"to":156.54,"location":2,"content":"When we talk about\ngame mechanics,"},{"from":156.54,"to":160.26,"location":2,"content":"you know, again, to\nme these are parts."},{"from":160.26,"to":163.27,"location":2,"content":"OK, and you know, it\ncan be a part that's"},{"from":163.27,"to":165.11,"location":2,"content":"been used many,\nmany times, or it"},{"from":165.11,"to":166.57,"location":2,"content":"can be a brand new\npart that you've"},{"from":166.57,"to":169.88,"location":2,"content":"invented all on your own."},{"from":169.88,"to":171.97,"location":2,"content":"And to me, you know,\nwhat really matters"},{"from":171.97,"to":174.83,"location":2,"content":"is the whole that's\nbuilt out of these parts."},{"from":174.83,"to":178.93,"location":2,"content":"You know, so I might\nhave, let's say, you know,"},{"from":178.93,"to":180,"location":2,"content":"a fuel injection unit, and an\nengine, and a differential,"},{"from":180,"to":183.25,"location":2,"content":"a fuel injection unit, and an\nengine, and a differential,"},{"from":183.25,"to":185.65,"location":2,"content":"and wheels, and I start\nputting these together"},{"from":185.65,"to":187.36,"location":2,"content":"to make some kind of a car."},{"from":187.36,"to":189.79,"location":2,"content":"And maybe I decide I want\na flux converter, you know,"},{"from":189.79,"to":191.46,"location":2,"content":"and I'm going to\ninvent a flux converter"},{"from":191.46,"to":192.7,"location":2,"content":"and stick it in there."},{"from":192.7,"to":195.43,"location":2,"content":"That's great, you know,\nbut what really matters"},{"from":195.43,"to":196.74,"location":2,"content":"is the entire car, you know."},{"from":196.74,"to":199.68,"location":2,"content":"How is that car going\nto drive or not?"},{"from":199.68,"to":201.22,"location":2,"content":"You know, with the\nexisting mechanics"},{"from":201.22,"to":203.52,"location":2,"content":"that we have right\nnow, obviously we"},{"from":203.52,"to":205.69,"location":2,"content":"can build, you know, a huge\nnumber of different kind"},{"from":205.69,"to":209.24,"location":2,"content":"of interactive experiences, but\nevery now and then, you know,"},{"from":209.24,"to":210,"location":2,"content":"you might want that\nflux converter."},{"from":210,"to":210.7,"location":2,"content":"you might want that\nflux converter."},{"from":210.7,"to":212.77,"location":2,"content":"You might want some\nbrand new thing."},{"from":212.77,"to":214.99,"location":2,"content":"I don't think it's that\nyou just kind of come up"},{"from":214.99,"to":217.49,"location":2,"content":"with a cool mechanic and\nsay, how do I use it?"},{"from":217.49,"to":220.72,"location":2,"content":"I think it's more like, here's\nan interactive experience"},{"from":220.72,"to":222.43,"location":2,"content":"that I want to create."},{"from":222.43,"to":224.23,"location":2,"content":"Now, what do I\nneed to create it?"},{"from":224.23,"to":225.82,"location":2,"content":"And if it turns\nout that, you know,"},{"from":225.82,"to":227.27,"location":2,"content":"there's something\nbrand new, you know,"},{"from":227.27,"to":229.77,"location":2,"content":"there's basically something you\nneed in this that you cannot"},{"from":229.77,"to":233.26,"location":2,"content":"figure out an existing mechanic\nthat will provide that,"},{"from":233.26,"to":234.97,"location":2,"content":"that's when you go\noff and make your own."},{"from":234.97,"to":238.94,"location":2,"content":"I am very happy to go off\nand make my own mechanics"},{"from":238.94,"to":240,"location":2,"content":"if I need to."},{"from":240,"to":240.27,"location":2,"content":"if I need to."},{"from":240.27,"to":241.69,"location":2,"content":"I don't even really\nthink about it"},{"from":241.69,"to":244.51,"location":2,"content":"so much in terms of, you know,\nthis is a new mechanic or not."},{"from":244.51,"to":246.79,"location":2,"content":"It's more like, this is the\nright mechanic, you know?"},{"from":246.79,"to":248.95,"location":2,"content":"Whether it was invented\nby me or somebody else,"},{"from":248.95,"to":250.99,"location":2,"content":"you know, I just, I think\nthere's always kind of,"},{"from":250.99,"to":253.84,"location":2,"content":"like, the right part to fill\nin that gap in your design."},{"from":253.84,"to":261.36,"location":2,"content":"[MUSIC PLAYING]"},{"from":261.36,"to":262.78,"location":2,"content":"If we talk about\nrules for a game,"},{"from":262.78,"to":266.41,"location":2,"content":"I think that they are almost,\nlike, two kinds of rules."},{"from":266.41,"to":268.45,"location":2,"content":"You know, there are\nthe really overt rules"},{"from":268.45,"to":270,"location":2,"content":"that you want to inform\nthe player about."},{"from":270,"to":270.56,"location":2,"content":"that you want to inform\nthe player about."},{"from":270.56,"to":273.27,"location":2,"content":"You know, you need to escape\nthe dungeon, or you know,"},{"from":273.27,"to":275.02,"location":2,"content":"this is a torch, you\nknow, whatever it is,"},{"from":275.02,"to":276.49,"location":2,"content":"you know, certain things you're\nvery clear with the player"},{"from":276.49,"to":276.94,"location":2,"content":"about."},{"from":276.94,"to":278.21,"location":2,"content":"Right off the bat,\nyou're going to say, OK,"},{"from":278.21,"to":280.54,"location":2,"content":"to control your character,\nyou use the [INAUDIBLE] keys,"},{"from":280.54,"to":281.47,"location":2,"content":"or this, or that."},{"from":281.47,"to":283.51,"location":2,"content":"So again, some something\nyou're very overt about."},{"from":283.51,"to":285.47,"location":2,"content":"And other things that\nthey discover-- you know,"},{"from":285.47,"to":287.8,"location":2,"content":"a trend that started\n10, 15 years ago"},{"from":287.8,"to":290.14,"location":2,"content":"is that part of the\ngameplay, the early gameplay,"},{"from":290.14,"to":292.93,"location":2,"content":"is the tutorial, and\nyou encounter objects,"},{"from":292.93,"to":296.12,"location":2,"content":"you know, as part of directed\ngameplay early on, and the game"},{"from":296.12,"to":298.66,"location":2,"content":"itself is kind of teaching you\nhow to use a sword in \"Zelda,\""},{"from":298.66,"to":300,"location":2,"content":"how to do this, how to do\nthat, how to cast a spell."},{"from":300,"to":301.11,"location":2,"content":"how to do this, how to do\nthat, how to cast a spell."},{"from":301.11,"to":302.85,"location":2,"content":"But then there are\na lot of other ones"},{"from":302.85,"to":304.6,"location":2,"content":"that you want to hide\nfrom the player that"},{"from":304.6,"to":306.61,"location":2,"content":"are under the hood,\nthat become mysterious."},{"from":306.61,"to":308.53,"location":2,"content":"And in a lot of ways,\nyou want your game world"},{"from":308.53,"to":311.91,"location":2,"content":"to be kind of a black\nbox at some level."},{"from":311.91,"to":314.53,"location":2,"content":"And this is actually, it kind of\ngets to the idea of immersion,"},{"from":314.53,"to":316.72,"location":2,"content":"that a lot of times somebody\nwill look at a system--"},{"from":316.72,"to":318.76,"location":2,"content":"when people look at the\nsimulation in \"Sim City,\""},{"from":318.76,"to":322.54,"location":2,"content":"they start imagining, you\nknow, this ungodly collection"},{"from":322.54,"to":324.94,"location":2,"content":"of mathematics and things\ncalculating this incredibly"},{"from":324.94,"to":326,"location":2,"content":"complicated city."},{"from":326,"to":327.71,"location":2,"content":"In fact, it's far,\nfar simpler than that."},{"from":327.71,"to":330,"location":2,"content":"You know, in fact, we found a\nfairly nice emergent system,"},{"from":330,"to":330.22,"location":2,"content":"You know, in fact, we found a\nfairly nice emergent system,"},{"from":330.22,"to":332.05,"location":2,"content":"so it was a fairly\nsimple set of rules"},{"from":332.05,"to":335.44,"location":2,"content":"that kind of emerged into\nthe complexity of a city"},{"from":335.44,"to":337.03,"location":2,"content":"simulation."},{"from":337.03,"to":338.89,"location":2,"content":"If players, you know,\nsaw under the hood,"},{"from":338.89,"to":340.47,"location":2,"content":"in some sense it\nwould kind of destroy"},{"from":340.47,"to":342.28,"location":2,"content":"a lot of the illusion\nof complexity"},{"from":342.28,"to":344.5,"location":2,"content":"there, the illusion of life."},{"from":344.5,"to":346.06,"location":2,"content":"It's very similar\nto the same reason"},{"from":346.06,"to":348,"location":2,"content":"why we didn't have\nthe Sims speak,"},{"from":348,"to":350.87,"location":2,"content":"you know, in a known language\nbecause as soon as they started"},{"from":350.87,"to":352.54,"location":2,"content":"repeating the same\nthings over and over,"},{"from":352.54,"to":354.55,"location":2,"content":"they would seem incredibly\nsimple and robotic."},{"from":354.55,"to":356.26,"location":2,"content":"But when you can't\nquite understand them,"},{"from":356.26,"to":358.66,"location":2,"content":"you tend to read in a lot more."},{"from":358.66,"to":360,"location":2,"content":"There was this thing that we\nstarted calling \"the simulator"},{"from":360,"to":361.12,"location":2,"content":"There was this thing that we\nstarted calling \"the simulator"},{"from":361.12,"to":364.09,"location":2,"content":"effect\" after watching\nthe first, you know,"},{"from":364.09,"to":366.57,"location":2,"content":"kind of batch of players\nplaying \"Sim City\" a lot,"},{"from":366.57,"to":368.2,"location":2,"content":"and then some of our\nlater games that--"},{"from":368.2,"to":370.12,"location":2,"content":"They would write letters to\nus, Oh, I love this game,"},{"from":370.12,"to":371.02,"location":2,"content":"and they would\ndescribe stuff that"},{"from":371.02,"to":372.12,"location":2,"content":"happened to them in\nthe game in letters"},{"from":372.12,"to":373.54,"location":2,"content":"they were writing to us."},{"from":373.54,"to":375.99,"location":2,"content":"And they would describe, you\nknow, things like, you know,"},{"from":375.99,"to":377.92,"location":2,"content":"the airplane crashed over here,\nand it hit the power line,"},{"from":377.92,"to":380.71,"location":2,"content":"and it caused a surge there, and\nthen this thing caught on fire."},{"from":380.71,"to":383.05,"location":2,"content":"And they would describe\nall these causal linkages"},{"from":383.05,"to":384.72,"location":2,"content":"that did not exist in the game."},{"from":384.72,"to":386.33,"location":2,"content":"You know, I knew\nthey did not exist,"},{"from":386.33,"to":387.79,"location":2,"content":"but in the player's\nhead, they did."},{"from":387.79,"to":390,"location":2,"content":"You know, nothing about the game\ndissuaded them from the fact,"},{"from":390,"to":391.78,"location":2,"content":"You know, nothing about the game\ndissuaded them from the fact,"},{"from":391.78,"to":394.06,"location":2,"content":"and so they were building\nup their own models"},{"from":394.06,"to":395.86,"location":2,"content":"of the way this\nsimulator was working,"},{"from":395.86,"to":399.17,"location":2,"content":"you know, that were very\nelaborate and interesting."},{"from":399.17,"to":400.59,"location":2,"content":"And that's when I\nkind of realized"},{"from":400.59,"to":402.71,"location":2,"content":"that there's certain parts\nof a simulator like that"},{"from":402.71,"to":404.46,"location":2,"content":"that you want to\nkeep a black box."},{"from":404.46,"to":407.05,"location":2,"content":"You know, the players,\nyou know, can actually"},{"from":407.05,"to":411.37,"location":2,"content":"imagine their own simulation\nusually far more interesting"},{"from":411.37,"to":413.71,"location":2,"content":"than yours, you know, as\nlong as you present them"},{"from":413.71,"to":417.48,"location":2,"content":"with enough scaffolding to\nbuild that in their imagination."},{"from":417.48,"to":419.98,"location":2,"content":"And so we ended up calling that\n\"the simulator effect,\" that"},{"from":419.98,"to":420,"location":2,"content":"when players are\nimagining that your,"},{"from":420,"to":421.69,"location":2,"content":"when players are\nimagining that your,"},{"from":421.69,"to":425.41,"location":2,"content":"your world or your simulation is\nmore detailed, more rich, more"},{"from":425.41,"to":429.35,"location":2,"content":"complicated than it actually\nis, don't talk them out of it."},{"from":429.35,"to":432.16,"location":2,"content":"And so, you know, part\nof exploring the world"},{"from":432.16,"to":436.1,"location":2,"content":"is, in fact, kind of uncovering\nthese loops of complexity"},{"from":436.1,"to":439.49,"location":2,"content":"in these rules, and so part of\nlearning the rules of the game"},{"from":439.49,"to":441.16,"location":2,"content":"are actually embedded\nin the game, which"},{"from":441.16,"to":442.21,"location":2,"content":"is actually very natural"},{"from":442.21,"to":449.25,"location":2,"content":"[MUSIC PLAYING]"},{"from":449.25,"to":450,"location":2,"content":"There's this thing\ncalled the Monte Carlo"},{"from":450,"to":450.96,"location":2,"content":"There's this thing\ncalled the Monte Carlo"},{"from":450.96,"to":454.44,"location":2,"content":"method, which is\nusing chance basically"},{"from":454.44,"to":455.82,"location":2,"content":"in the place of calculus."},{"from":455.82,"to":457.92,"location":2,"content":"You know, a lot of things\nthat would be simulated"},{"from":457.92,"to":459.48,"location":2,"content":"in the natural\nworld, you know, we"},{"from":459.48,"to":463.11,"location":2,"content":"have established mathematics,\nwhich is linear calculus."},{"from":463.11,"to":465.12,"location":2,"content":"But it turns out that\nfor most of these things"},{"from":465.12,"to":467.7,"location":2,"content":"with a computer, there's a whole\nother approach that basically"},{"from":467.7,"to":470.1,"location":2,"content":"can solve the same set of\nproblems, which is basically"},{"from":470.1,"to":472.29,"location":2,"content":"throwing darts at a\ndartboard, and you"},{"from":472.29,"to":475.59,"location":2,"content":"have shapes on that dartboard\nthat are about, you know,"},{"from":475.59,"to":476.29,"location":2,"content":"the right area."},{"from":476.29,"to":477.66,"location":2,"content":"I'm going to go\nto the whiteboard"},{"from":477.66,"to":480,"location":2,"content":"to kind of give you a simple\nlittle illustration of this."},{"from":480,"to":480.03,"location":2,"content":"to kind of give you a simple\nlittle illustration of this."},{"from":480.03,"to":485.37,"location":2,"content":" "},{"from":485.37,"to":486.87,"location":2,"content":"And just to keep\nit very simple, you"},{"from":486.87,"to":490.54,"location":2,"content":"know, let's assume\nthat we have some area"},{"from":490.54,"to":492.5,"location":2,"content":"and that we have within\nthat area some regions."},{"from":492.5,"to":494.08,"location":2,"content":"You know, and maybe\nthis is the amount"},{"from":494.08,"to":497.13,"location":2,"content":"of area developed, you know,\nin \"Sim City,\" or the areas"},{"from":497.13,"to":499.47,"location":2,"content":"with police coverage,\nwhatever it is."},{"from":499.47,"to":501.84,"location":2,"content":"Now, normally if you\nwanted to measure"},{"from":501.84,"to":505.47,"location":2,"content":"what percentage of\nthis entire area"},{"from":505.47,"to":508.47,"location":2,"content":"is occupied by these\nblobs, you know,"},{"from":508.47,"to":510,"location":2,"content":"there's some very\nelaborate mathematics kind"},{"from":510,"to":510.45,"location":2,"content":"there's some very\nelaborate mathematics kind"},{"from":510.45,"to":511.9,"location":2,"content":"of going down the\ncalculus path that you"},{"from":511.9,"to":513.49,"location":2,"content":"would use to measure\nthat and give you"},{"from":513.49,"to":514.6,"location":2,"content":"a pretty accurate answer."},{"from":514.6,"to":516.2,"location":2,"content":"But if you have a\ncomputer, you know,"},{"from":516.2,"to":517.69,"location":2,"content":"and computers are\nvery fast and good"},{"from":517.69,"to":519.57,"location":2,"content":"at just doing simple\nthings repetitively,"},{"from":519.57,"to":521.17,"location":2,"content":"it turns out there's a\nmuch simpler technique,"},{"from":521.17,"to":523.2,"location":2,"content":"and they call this the\nMonte Carlo method, which"},{"from":523.2,"to":525.9,"location":2,"content":"is that we just sit here, and\nwe just randomly throw darts"},{"from":525.9,"to":527.41,"location":2,"content":"at this board."},{"from":527.41,"to":532.98,"location":2,"content":"You know, and then we just count\nover time how many of the darts"},{"from":532.98,"to":536.76,"location":2,"content":"land inside of these areas,\nand how many land outside."},{"from":536.76,"to":539.29,"location":2,"content":"And you know, you throw a\nfew hundred darts at there,"},{"from":539.29,"to":540,"location":2,"content":"you know, and it turns\nout that, you know,"},{"from":540,"to":541.04,"location":2,"content":"you know, and it turns\nout that, you know,"},{"from":541.04,"to":545.55,"location":2,"content":"let's say out of 100 darts,\nyou know, 67 land outside"},{"from":545.55,"to":551.13,"location":2,"content":"of these zones, and let's\nsay 33 land inside the zones."},{"from":551.13,"to":552.3,"location":2,"content":"That's the basic percentage."},{"from":552.3,"to":555.09,"location":2,"content":"You basically-- that's\n33% of the area of that."},{"from":555.09,"to":558.72,"location":2,"content":"This is the kind of, you know,\nsimple mathematics, you know,"},{"from":558.72,"to":560.7,"location":2,"content":"that we use a lot\nin simulations."},{"from":560.7,"to":562.98,"location":2,"content":"And so this, in fact,\nis relying very much"},{"from":562.98,"to":567.03,"location":2,"content":"on these probabilities,\nand it's the way"},{"from":567.03,"to":569.37,"location":2,"content":"a lot of the emergence\nthat we get out of some"},{"from":569.37,"to":570,"location":2,"content":"of these systems works as well."},{"from":570,"to":571.51,"location":2,"content":"of these systems works as well."},{"from":571.51,"to":572.97,"location":2,"content":"So from the design\npoint of view,"},{"from":572.97,"to":576,"location":2,"content":"it's amazing how you can build\nsuper simple things like that"},{"from":576,"to":578.94,"location":2,"content":"in place of what used to be very\nkind of elaborate mathematics."},{"from":578.94,"to":586.66,"location":2,"content":"[MUSIC PLAYING]"},{"from":586.66,"to":588.99,"location":2,"content":"There's another kind of chance,\nthough, that I encounter"},{"from":588.99,"to":591.57,"location":2,"content":"as a designer, which\nis that a lot of times"},{"from":591.57,"to":594.78,"location":2,"content":"I'll be making something,\ndoing prototypes, whatever,"},{"from":594.78,"to":597.66,"location":2,"content":"and something just\npops up unexpectedly."},{"from":597.66,"to":599.88,"location":2,"content":"You know, either we made a,\nput a bug in the program,"},{"from":599.88,"to":600,"location":2,"content":"or it's not behaving\nthe way I thought,"},{"from":600,"to":601.86,"location":2,"content":"or it's not behaving\nthe way I thought,"},{"from":601.86,"to":605.34,"location":2,"content":"or something happens\nthat surprises me."},{"from":605.34,"to":609.39,"location":2,"content":"And through pure chance, I might\ntrip over some new mechanic,"},{"from":609.39,"to":610.23,"location":2,"content":"or some new feature."},{"from":610.23,"to":612.59,"location":2,"content":"Or that reminds me of this;\nlet's try that, you know."},{"from":612.59,"to":613.8,"location":2,"content":"And this is like serendipity."},{"from":613.8,"to":616.05,"location":2,"content":"This is me, you know, kind\nof accidentally discovering"},{"from":616.05,"to":618.87,"location":2,"content":"something very cool, you\nknow, either in prototyping,"},{"from":618.87,"to":620.67,"location":2,"content":"or testing, or\njust even on paper"},{"from":620.67,"to":622.8,"location":2,"content":"as I'm kind of thinking\nthrough a design that"},{"from":622.8,"to":625.01,"location":2,"content":"causes me to go off in a\ntotally different direction,"},{"from":625.01,"to":627.18,"location":2,"content":"you know, tangent to where\nI was going initially."},{"from":627.18,"to":629.37,"location":2,"content":"Now, this is often the\ndesigner's point of view, you"},{"from":629.37,"to":630,"location":2,"content":"how, kind of how you use\nprobability to your advantage."},{"from":630,"to":632.97,"location":2,"content":"how, kind of how you use\nprobability to your advantage."},{"from":632.97,"to":635.02,"location":2,"content":"You know, from the\nplayer's point of view,"},{"from":635.02,"to":637.53,"location":2,"content":"you know, again, there'll\nbe a lot of things happening"},{"from":637.53,"to":639.24,"location":2,"content":"in your game that\nmight be purely random,"},{"from":639.24,"to":641.03,"location":2,"content":"you know, and you know\nthat they're random."},{"from":641.03,"to":643.71,"location":2,"content":"The players are always going to\nbe trying to assign causality"},{"from":643.71,"to":644.31,"location":2,"content":"to something."},{"from":644.31,"to":646.2,"location":2,"content":"You know, if all of a\nsudden that torch goes out,"},{"from":646.2,"to":648.12,"location":2,"content":"or there's a sound over there,\nthe player in their head"},{"from":648.12,"to":649.87,"location":2,"content":"is going to be\nbuilding some model of,"},{"from":649.87,"to":651.06,"location":2,"content":"what caused that to happen?"},{"from":651.06,"to":652.05,"location":2,"content":"Was it something I did?"},{"from":652.05,"to":653.55,"location":2,"content":"Is it some something\nthat caters it,"},{"from":653.55,"to":655.17,"location":2,"content":"foreshadowing of some event?"},{"from":655.17,"to":657.75,"location":2,"content":"And I think that\nyou actually want"},{"from":657.75,"to":659.13,"location":2,"content":"kind of a balance\nthere a little,"},{"from":659.13,"to":660,"location":2,"content":"you know, kind of\n[INAUDIBLE] noise"},{"from":660,"to":661.05,"location":2,"content":"you know, kind of\n[INAUDIBLE] noise"},{"from":661.05,"to":664.03,"location":2,"content":"so that there's some stuff\nhappening in the world that,"},{"from":664.03,"to":665.82,"location":2,"content":"again, remains kind of\na black box to them,"},{"from":665.82,"to":667.61,"location":2,"content":"whether, you know, from\ntheir point of view"},{"from":667.61,"to":670.83,"location":2,"content":"it's random chance, or it's\nsome elaborate, deep, you know,"},{"from":670.83,"to":674.42,"location":2,"content":"behavior of your, you know,\nyour world the player is going"},{"from":674.42,"to":676.42,"location":2,"content":"to assume it's some deep\nbehavior of your world,"},{"from":676.42,"to":677.45,"location":2,"content":"I think, in most cases."},{"from":677.45,"to":679.53,"location":2,"content":"But if it's something that\nthe player did, and you"},{"from":679.53,"to":681.72,"location":2,"content":"want clear feedback that\nthe player did this,"},{"from":681.72,"to":683.91,"location":2,"content":"and the door\nunlocked, that's when"},{"from":683.91,"to":686.37,"location":2,"content":"you have to make sure you're\ngetting above that, that noise"},{"from":686.37,"to":688.33,"location":2,"content":"level, and it's totally\nsignaled to the player."},{"from":688.33,"to":690,"location":2,"content":"And so you need to make sure\nthat the feedback you're"},{"from":690,"to":690.54,"location":2,"content":"And so you need to make sure\nthat the feedback you're"},{"from":690.54,"to":692.25,"location":2,"content":"giving to the player\nis signal and not"},{"from":692.25,"to":695.76,"location":2,"content":"noise against this kind\nof random world churning."},{"from":695.76,"to":703.03,"location":2,"content":"[MUSIC PLAYING]"},{"from":703.03,"to":707.75,"location":2,"content":"Well, because my games don't\nhave an overt in-state,"},{"from":707.75,"to":709.25,"location":2,"content":"you know, I don't\nthink it really"},{"from":709.25,"to":711.86,"location":2,"content":"changes the nature\nof wanting to present"},{"from":711.86,"to":715.44,"location":2,"content":"an interesting, challenging\nkind of creative world."},{"from":715.44,"to":717.02,"location":2,"content":"I don't think that--\nyou know, I think"},{"from":717.02,"to":718.52,"location":2,"content":"that's kind of\nalmost, worldbuilding"},{"from":718.52,"to":720,"location":2,"content":"is almost a different\nkind of level to that."},{"from":720,"to":722.25,"location":2,"content":"is almost a different\nkind of level to that."},{"from":722.25,"to":724.51,"location":2,"content":"The chance and probability--"},{"from":724.51,"to":726.89,"location":2,"content":"for a player, you know, again,\nit can depend on the game."},{"from":726.89,"to":728.51,"location":2,"content":"If, you know, you're\nplaying Casino games,"},{"from":728.51,"to":729.93,"location":2,"content":"you know, you're\nkind of expecting"},{"from":729.93,"to":732.63,"location":2,"content":"these things to be based\naround chance and probability."},{"from":732.63,"to":734.96,"location":2,"content":"If you're playing something\nlike a first-person shooter,"},{"from":734.96,"to":737.79,"location":2,"content":"you're kind of imagining that,\nyou know, if I aim at that guy,"},{"from":737.79,"to":738.91,"location":2,"content":"it's going to hit that guy."},{"from":738.91,"to":741.56,"location":2,"content":"You know, I don't want a\nchance of having a dud bullet,"},{"from":741.56,"to":743.87,"location":2,"content":"or my bullet, you know,\ngoing off target just"},{"from":743.87,"to":745.05,"location":2,"content":"through random chance."},{"from":745.05,"to":747.32,"location":2,"content":"So I want my actions\nto be clearly,"},{"from":747.32,"to":750,"location":2,"content":"you know, kind of almost\ndeterministic in that sense."},{"from":750,"to":750.29,"location":2,"content":"you know, kind of almost\ndeterministic in that sense."},{"from":750.29,"to":751.79,"location":2,"content":"So I think it depends\non the feature"},{"from":751.79,"to":753.71,"location":2,"content":"of your world as to what\nyou're talking about."},{"from":753.71,"to":755.78,"location":2,"content":"If it's something like\n\"Sim City,\" and, you know,"},{"from":755.78,"to":757.47,"location":2,"content":"when does a fire occur?"},{"from":757.47,"to":760.11,"location":2,"content":"You know, that actually is a\nlittle bit of a combination."},{"from":760.11,"to":761.53,"location":2,"content":"It's a combination\nof, how much am"},{"from":761.53,"to":762.93,"location":2,"content":"I done with my fire services?"},{"from":762.93,"to":764.06,"location":2,"content":"But there's still a chance."},{"from":764.06,"to":767.24,"location":2,"content":"It's changing the probability\nof a fire actually happening."},{"from":767.24,"to":769.97,"location":2,"content":"It could still happen even\nif I have good fire coverage,"},{"from":769.97,"to":771.89,"location":2,"content":"but the chance is lower."},{"from":771.89,"to":774.56,"location":2,"content":"And you know, for\nthe player, you know,"},{"from":774.56,"to":777.53,"location":2,"content":"that's kind of the expectation\ncoming into a world like that,"},{"from":777.53,"to":779.03,"location":2,"content":"and so really, I\nthink at that point"},{"from":779.03,"to":780,"location":2,"content":"you're really kind\nof falling back into,"},{"from":780,"to":780.17,"location":2,"content":"you're really kind\nof falling back into,"},{"from":780.17,"to":782.15,"location":2,"content":"what feels like an\nexpectation of the player?"},{"from":782.15,"to":784.15,"location":2,"content":"You don't want the world\nto feel like, you know,"},{"from":784.15,"to":786.61,"location":2,"content":"arbitrary things are happening\nfor absolutely no reason."},{"from":786.61,"to":788.69,"location":2,"content":"You know, so even when a\nfire occurs in \"Sim City\""},{"from":788.69,"to":790.46,"location":2,"content":"when there's a low\nprobability, the player"},{"from":790.46,"to":791.58,"location":2,"content":"can imagine that occurring."},{"from":791.58,"to":794.04,"location":2,"content":"You know, it's not an\nunimaginable situation."},{"from":794.04,"to":795.5,"location":2,"content":"What you really\ndon't want to do is"},{"from":795.5,"to":797.66,"location":2,"content":"you don't want the\ngame to feel capricious"},{"from":797.66,"to":800.04,"location":2,"content":"in terms of killing the\nplayer for no obvious reason."},{"from":800.04,"to":803.73,"location":2,"content":"You know, that, you know,\nis really a major no-no."},{"from":803.73,"to":806.42,"location":2,"content":"The player always wants to feel\nlike their success or failure"},{"from":806.42,"to":807.81,"location":2,"content":"is coming back to their agency."},{"from":807.81,"to":808.91,"location":2,"content":"You know, it's\ntheir fault. They're"},{"from":808.91,"to":810,"location":2,"content":"the ones responsible\nfor their own fate."},{"from":810,"to":810.58,"location":2,"content":"the ones responsible\nfor their own fate."},{"from":810.58,"to":818.55,"location":2,"content":"[MUSIC PLAYING]"},{"from":818.55,"to":820.43,"location":2,"content":"Depending on the kind\nof game you're doing,"},{"from":820.43,"to":823.1,"location":2,"content":"you know, it does put the player\ninto a certain kind of mindset,"},{"from":823.1,"to":825,"location":2,"content":"and they build a\ncertain kind of model,"},{"from":825,"to":828.18,"location":2,"content":"whether it's like a first-person\nkind of game with exploration"},{"from":828.18,"to":831.3,"location":2,"content":"and combat, or it's a\nthird-person game with resource"},{"from":831.3,"to":835.11,"location":2,"content":"management, you know,\nthey all, at some level,"},{"from":835.11,"to":837.99,"location":2,"content":"share a set of features, share,\nyou know, certain amounts"},{"from":837.99,"to":840,"location":2,"content":"of player agency."},{"from":840,"to":840.06,"location":2,"content":"of player agency."},{"from":840.06,"to":841.53,"location":2,"content":"They share world dynamics."},{"from":841.53,"to":844.14,"location":2,"content":"You know, so that's the level\nat which these things are all"},{"from":844.14,"to":845.97,"location":2,"content":"pretty common across there."},{"from":845.97,"to":848.16,"location":2,"content":"But you know, I\nthink there are so"},{"from":848.16,"to":851.76,"location":2,"content":"many game mechanics that have\nbeen used and so many more yet"},{"from":851.76,"to":853.33,"location":2,"content":"to be discovered."},{"from":853.33,"to":855.48,"location":2,"content":"I think the designer\nwill develop an intuition"},{"from":855.48,"to":857.03,"location":2,"content":"for which one of\nthese things they"},{"from":857.03,"to":858.79,"location":2,"content":"want to put into\ntheir palette of tools"},{"from":858.79,"to":861.12,"location":2,"content":"and which ones they want to\nbecome a master at because I"},{"from":861.12,"to":863.43,"location":2,"content":"think that certain game\ndesigners, you know,"},{"from":863.43,"to":864.9,"location":2,"content":"get very specialized\nand very good,"},{"from":864.9,"to":866.73,"location":2,"content":"you know, within certain\nkind of mechanics,"},{"from":866.73,"to":869.39,"location":2,"content":"using certain parts\nto build their games."},{"from":869.39,"to":870,"location":2,"content":"And over time, you know, you'll\nstart expanding that palette."},{"from":870,"to":871.93,"location":2,"content":"And over time, you know, you'll\nstart expanding that palette."},{"from":871.93,"to":872.67,"location":2,"content":"You'll start trying other ones."},{"from":872.67,"to":874.47,"location":2,"content":"You'll play other games, games\nthat you would not normally"},{"from":874.47,"to":876.42,"location":2,"content":"play, and just to kind\nof get a sense of what"},{"from":876.42,"to":877.5,"location":2,"content":"those mechanics feel like."},{"from":877.5,"to":879.2,"location":2,"content":"Is that a tool that\nI could use, a part"},{"from":879.2,"to":880.68,"location":2,"content":"that I can use next time\nI build, you know, one"},{"from":880.68,"to":881.85,"location":2,"content":"of my game engines?"},{"from":881.85,"to":884.55,"location":2,"content":"I think for most designers,\nyou know, get familiar."},{"from":884.55,"to":887.07,"location":2,"content":"Get some mastery\nand skill at, you"},{"from":887.07,"to":889.1,"location":2,"content":"know, using a certain\nkind of mechanics."},{"from":889.1,"to":891.42,"location":2,"content":"At the same time, always\nbe looking at new ones"},{"from":891.42,"to":893.09,"location":2,"content":"and trying to imagine,\nyou know, could I"}]}